text2mapviewer/__init__.py
text2mapviewer/main.py
text2mapviewer/examples/map_embedding.py
text2mapviewer/examples/map_embedding_click.py
text2mapviewer/examples/map_text_embedding.py
text2mapviewer/fondamental/bases.py
text2mapviewer-0.2.2.dist-info/LICENSE
text2mapviewer-0.2.2.dist-info/METADATA
text2mapviewer-0.2.2.dist-info/WHEEL
text2mapviewer-0.2.2.dist-info/top_level.txt
text2mapviewer-0.2.2.dist-info/RECORD
