Metadata-Version: 2.1
Name: text2mapviewer
Version: 0.2.2
Summary: A python package to map your own csv files data using Atlas from NOMIC
Author-email: Papa Séga WADE <pasega.wade@gmail.com>
Project-URL: Homepage, https://github.com/papasega/text2mapviewer
Keywords: Embedding, Visualization, Map, Text, CSV,  Search keywords, Dynamic
Classifier: Programming Language :: Python :: 3
Classifier: License :: OSI Approved :: MIT License
Classifier: Operating System :: OS Independent
Requires-Python: >=3.7
License-File: LICENSE
Requires-Dist: click
Requires-Dist: torch
Requires-Dist: transformers
Requires-Dist: sentence-transformers
Requires-Dist: nomic
Requires-Dist: numpy
Requires-Dist: pandas
